pytly/__init__.py
pytly/pytly.py
pytly-0.0.10.dist-info/METADATA
pytly-0.0.10.dist-info/WHEEL
pytly-0.0.10.dist-info/licenses/LICENSE
pytly-0.0.10.dist-info/RECORD
